[
  {
    "name": "Camera",
    "loc": [
      7.358891,
      -6.925791,
      4.958309
    ],
    "rot": [
      1.109319,
      0.0,
      0.814928
    ],
    "scale": [
      1.0,
      1.0,
      1.0
    ],
    "modified_by": "sanyam",
    "modified_at": "2026-03-28T00:20:07"
  },
  {
    "name": "Cube",
    "loc": [
      0.0,
      5.0,
      0.0
    ],
    "rot": [
      0.0,
      0.0,
      0.0
    ],
    "scale": [
      1.0,
      1.0,
      1.0
    ],
    "modified_by": "sanyam",
    "modified_at": "2026-03-28T00:25:25"
  },
  {
    "name": "Light",
    "loc": [
      4.076245,
      1.005454,
      5.903862
    ],
    "rot": [
      0.650328,
      0.055217,
      1.866391
    ],
    "scale": [
      1.0,
      1.0,
      1.0
    ],
    "modified_by": "sanyam",
    "modified_at": "2026-03-28T00:20:07"
  }
]